{
  "company": "Kuraray Europe GmbH",
  "hall": "7a",
  "stand": "D06",
  "address": "Germany",
  "email": null,
  "phone": "+49 211 4560-01",
  "website": "https://go.kuraray.com/k2025",
  "contact_person": null,
  "products": null,
  "description": "Skip to main content\nSupport\nSearch\nENGLISH\nTicket shop\nHome\nExhibit\nVisit\nExhibitors & Products\nProgramme\nMedia & News\nK-Alliance\nProfile\nProducts\nStand\nCompany news\nBookmark\nShare profile\nExhibitor may contact me\nLanguage\nKuraray Europe GmbH\nHall 7a / D06\nGermany, Hattersheim\nPlay\nPrevious\n1/2\nNext\nExclusive K Show Landing Page: https://go.kuraray.com/k2025\n\nAbout Kuraray\nKuraray Europe GmbH was founded in 1991.",
  "profile_url": "https://www.k-online.com/vis/v1/en/exhprofiles/Uo8GPyB5SjiauptqAE2uSw",
  "contacts": []
}